{
    "npc-escorts": [
        {
            "name": "battlethreads",
            "hp": [10, 10],
            "defense": 8,
            "tags": ["unique"],
            "abilities": [
                {
                    "type": "Trait",
                    "name": "Fleet Appendage",
                    "effect": ""
                },
                {
                    "type": "Tactic",
                    "name": "Local Legion Gestalt",
                    "effect": ""
                }
            ]
        },
        {
            "name": "brothers-in-arms",
            "hp": [8, 8],
            "defense": 8,
            "tags": [],
            "abilities": [
                {
                    "type": "Trait",
                    "name": "Tender Comerade",
                    "effect": ""
                },
                {
                    "type": "Gun",
                    "name": "Short-Spool Spinal Guns",
                    "effect": "",
                    "range": "4-1",
                    "size": "Superheavy",
                    "target": "Single",
                    "charge": 2,
                    "dammage": 12
                }
            ]
        },
        {
            "name": "daggerflight",
            "hp": [6, 6, 6, 6],
            "defense": 10,
            "tags": []
        },
        {
            "name": "den-mother",
            "+hp": 5,
            "+defense": 0,
            "tags": ["template"],
            "wings": {
                "name": "mounted chassis",
                "hp": [5, 5, 5, 5],
                "range": "0-3",
                "tenacity": 11
            }
        },
        {
            "name": "diluvia",
            "hp": [18],
            "defense": 8,
            "tags": []
        },
        {
            "name": "giant",
            "+hp": 20,
            "+defense": -2,
            "tags": ["template"],
            "abilities":[
                {
                    "type": "Gun",
                    "name": "Tyrant-Cannon",
                    "effect": "",
                    "range": "5-4",
                    "size": "Superheavy",
                    "target": "Single",
                    "tags": ["critical", "reliable(10)"],
                    "charge": 4,
                    "dammage": 30
                }
            ]
        },
        {
            "name": "loyal-guardian",
            "hp": [20],
            "defense": 8,
            "tags": ["unique"]
        },
        {
            "name": "mastermind",
            "tags": ["template"]
        },
        {
            "name": "roughnecks",
            "hp": [8, 8],
            "defense": 10,
            "+interdiction": "2",
            "tags": []
        },
        {
            "name": "starfield-furies",
            "hp": [10, 10],
            "defense": 8,
            "tags": [],
            "wings": [{
                "name": "fighter",
                "hp": [5, 5],
                "range": "0-2",
                "assiciate": 0
            },
            {
                "name": "bomber",
                "hp": [6],
                "range": "0-2",
                "assiciate": 0
            },
            {
                "name": "fighter",
                "hp": [5, 5],
                "range": "0-2",
                "assiciate": 1
            },
            {
                "name": "bomber",
                "hp": [6],
                "range": "0-2",
                "assiciate": 1
            }
            ]
        },
        {
            "name": "stalwards",
            "hp": [10, 10],
            "defense": 8,
            "tags": []
        },
        {
            "name": "wardogs",
            "hp": [8, 8],
            "defense": 10,
            "tags": []
        },
        {
            "name": "[unknown]",
            "+hp": 5,
            "tags": ["template"],
            "abilities":[
                {
                    "type": "Gun",
                    "name": "Naophoros-Omnigun",
                    "effect": "",
                    "range": "5-0",
                    "size": "Superheavy",
                    "target": "Single",
                    "charge": -1,
                    "dammage": 0
                }
            ]
        }
    ],
    "npc-capital": [
        {
            "name": "breakwater",
            "hp": 25,
            "defense": 10,
            "interdiction": "1d6",
            "wings": {
                "name": "fighter/bomber-squadron",
                "hp": [5, 5, 5, 5],
                "range": "0-3"
            }
        },
        {
            "name": "cornicen",
            "hp": 25,
            "defense": 10,
            "interdiction": "1d6"
        },
        {
            "name": "corsair",
            "hp": 25,
            "defense": 10,
            "interdiction": "1d6",
            "wings": {
                "name": "motely-crew",
                "hp": [5, 5, 5, 5],
                "range": "0-3",
                "tenacity": 12
            }
        },
        {
            "name": "highline",
            "hp": 20,
            "defense": 10,
            "interdiction": "1d6+4"
        },
        {
            "name": "hivequeen",
            "hp": 30,
            "defense": 8,
            "interdiction": "2d6"
        },
        {
            "name": "man-o-war",
            "hp": 30,
            "defense": 6,
            "interdiction": "2d6",
            "abilities":[
                {
                    "type": "Gun",
                    "name": "Demisolar-Lance",
                    "effect": "",
                    "range": "5-3",
                    "size": "Superheavy",
                    "target": "Single",
                    "tags": ["accurate", "critical"],
                    "charge": 4,
                    "dammage": 20
                }
            ]
        },
        {
            "name": "narcissus",
            "hp": 16,
            "defense": 10,
            "interdiction": "1d6"
        },
        {
            "name": "needleship",
            "hp": 25,
            "defense": 12,
            "interdiction": "1d6"
        },
        {
            "name": "paladin",
            "hp": 25,
            "defense": 8,
            "interdiction": "2d6",
            "abilities":[
                {
                    "type": "Gun",
                    "name": "Redgiant-Solar-Lance",
                    "effect": "",
                    "range": "5-2",
                    "size": "Superheavy",
                    "target": "Single",
                    "tags": ["reliable(5)", "critical"],
                    "charge": 3,
                    "dammage": 15
                }
            ]
        },
        {
            "name": "phantasm",
            "hp": 20,
            "defense": 15,
            "interdiction": "1d6",
            "abilities":[
                {
                    "type": "Gun",
                    "name": "killdart-coherent-nuclear-actuated-laser",
                    "effect": "",
                    "range": "4-1",
                    "size": "Superheavy",
                    "target": "Single",
                    "tags": ["reliable(5)", "critical"],
                    "charge": 3,
                    "dammage": 15
                }
            ]
        },
        {
            "name": "starkiller",
            "hp": 25,
            "defense": 8,
            "interdiction": "2d6",
            "abilities":[
                {
                    "type": "Gun",
                    "name": "killdart-coherent-nuclear-actuated-laser",
                    "effect": "",
                    "range": "5-3",
                    "size": "Superheavy",
                    "target": "Single",
                    "tags": ["critical"],
                    "charge": 2,
                    "dammage": 15
                }
            ]
        },
        {
            "name": "triton",
            "hp": 30,
            "defense": 6,
            "interdiction": "3d6"
        },
        {
            "name": "turtleback",
            "hp": 35,
            "defense": 6,
            "interdiction": "1d6"
        }
    ]
}
